odoo/addons/hr_timesheet_date_order_desc/README.rst
odoo/addons/hr_timesheet_date_order_desc/__init__.py
odoo/addons/hr_timesheet_date_order_desc/__manifest__.py
odoo/addons/hr_timesheet_date_order_desc/i18n/hr_timesheet_date_order_desc.pot
odoo/addons/hr_timesheet_date_order_desc/i18n/it.po
odoo/addons/hr_timesheet_date_order_desc/readme/CONTRIBUTORS.md
odoo/addons/hr_timesheet_date_order_desc/readme/DESCRIPTION.md
odoo/addons/hr_timesheet_date_order_desc/static/description/icon.png
odoo/addons/hr_timesheet_date_order_desc/static/description/index.html
odoo/addons/hr_timesheet_date_order_desc/views/hr_analytic_timesheet.xml
odoo_addon_hr_timesheet_date_order_desc-17.0.1.0.0.2.dist-info/METADATA
odoo_addon_hr_timesheet_date_order_desc-17.0.1.0.0.2.dist-info/WHEEL
odoo_addon_hr_timesheet_date_order_desc-17.0.1.0.0.2.dist-info/top_level.txt
odoo_addon_hr_timesheet_date_order_desc-17.0.1.0.0.2.dist-info/RECORD
